csvkitcat/__about__.py
csvkitcat/__init__.py
csvkitcat/agatable.py
csvkitcat/alltext.py
csvkitcat/chartable.py
csvkitcat/exceptions.py
csvkitcat/pandashelper.py
csvkitcat-1.6.1a0.dist-info/AUTHORS.rst
csvkitcat-1.6.1a0.dist-info/COPYING
csvkitcat-1.6.1a0.dist-info/METADATA
csvkitcat-1.6.1a0.dist-info/WHEEL
csvkitcat-1.6.1a0.dist-info/entry_points.txt
csvkitcat-1.6.1a0.dist-info/top_level.txt
csvkitcat-1.6.1a0.dist-info/RECORD
