Metadata-Version: 2.1
Name: csvkitcat
Version: 1.6.1a0
Summary: 'The unofficial extended family of csvkit: semi-awkward tools for command-line data parsing
Home-page: https://github.com/dannguyen/csvkitcat
Author: Dan Nguyen
Author-email: dansonguyen@gmail.com
License: MIT
Project-URL: Documentation, https://csvkitcat.readthedocs.io/en/latest/
Platform: UNKNOWN
Classifier: Development Status :: 3 - Alpha
Classifier: Environment :: Console
Classifier: Intended Audience :: Developers
Classifier: Intended Audience :: End Users/Desktop
Classifier: Intended Audience :: Science/Research
Classifier: License :: OSI Approved :: MIT License
Classifier: Natural Language :: English
Classifier: Operating System :: OS Independent
Classifier: Programming Language :: Python
Classifier: Programming Language :: Python :: 3.6
Classifier: Programming Language :: Python :: 3.7
Classifier: Programming Language :: Python :: 3.8
Classifier: Programming Language :: Python :: Implementation :: CPython
Classifier: Programming Language :: Python :: Implementation :: PyPy
Classifier: Topic :: Scientific/Engineering :: Information Analysis
Classifier: Topic :: Software Development :: Libraries :: Python Modules
Classifier: Topic :: Utilities
Requires-Dist: csvkit (>=1.0.5)
Requires-Dist: altair (>=4.1)
Requires-Dist: altair-viewer (>=0.3.0)
Requires-Dist: python-slugify (>=4.0)
Requires-Dist: regex (>=2020.7.14)
Provides-Extra: dev
Requires-Dist: coverage (>=4.4.2) ; extra == 'dev'
Requires-Dist: nose (>=1.1.2) ; extra == 'dev'
Requires-Dist: sphinx (>=1.0.7) ; extra == 'dev'
Requires-Dist: sphinx-rtd-theme ; extra == 'dev'
Requires-Dist: tox (>=3.1.0) ; extra == 'dev'
